README.md
setup.py
keras_clinical/__init__.py
keras_clinical.egg-info/PKG-INFO
keras_clinical.egg-info/SOURCES.txt
keras_clinical.egg-info/dependency_links.txt
keras_clinical.egg-info/requires.txt
keras_clinical.egg-info/top_level.txt