Metadata-Version: 1.0
Name: keras-clinical
Version: 1.0
Summary: Keras Implemented Clinical Model Zoo.
Home-page: UNKNOWN
Author: Ben Neely
Author-email: nigelneely@gmail.com
License: MIT
Platform: UNKNOWN
